{"id":86,"firstName":"Rupert","lastName":"Upton","maidenName":"Schuster","age":22,"gender":"male","email":"whuman2d@hp.com","phone":"+1 907 460 1257","username":"whuman2d","password":"JyHAUcC","birthDate":"2003-04-04","image":"https://robohash.org/mollitiasimiliqueneque.png","bloodGroup":"O+","height":156,"weight":95.4,"eyeColor":"Amber","hair":{"color":"Auburn","type":"Straight"},"domain":"usgs.gov","ip":"104.39.129.116","address":{"address":"1770 Colony Way","city":"Fayetteville","coordinates":{"lat":36.0867,"lng":-94.229754},"postalCode":"72704","state":"AR"},"macAddress":"51:28:40:44:E0:58","university":"Instituto Tecnológico de Santo Domingo","bank":{"cardExpire":"01/24","cardNumber":"5455601481585424","cardType":"diners-club-us-ca","currency":"Peso","iban":"FR22 3683 1735 92L6 3ORW B8LQ 375"},"company":{"address":{"address":"1649 Timberridge Court","city":"Fayetteville","coordinates":{"lat":36.084563,"lng":-94.206082},"postalCode":"72704","state":"AR"},"department":"Sales","name":"Gaylord, Mohr and Ruecker","title":"Cost Accountant"},"ein":"40-3998807","ssn":"679-41-9289","userAgent":"Mozilla/5.0 (Windows NT 6.0) AppleWebKit/534.24 (KHTML, like Gecko) Chrome/11.0.696.3 Safari/534.24"}